tencent_apigateway_common/__init__.py
tencent_apigateway_common/django/__init__.py
tencent_apigateway_common/django/translation.py
tencent_apigateway_common/encrypt/__init__.py
tencent_apigateway_common/encrypt/cipher.py
tencent_apigateway_common/env.py
tencent_apigateway_common/i18n/__init__.py
tencent_apigateway_common/i18n/field.py
tencent_apigateway_common/pypi/__init__.py
tencent_apigateway_common/pypi/pip.py
tencent_apigateway_common/pypi/registry.py
tencent_apigateway_common/secure/__init__.py
tencent_apigateway_common/secure/dj_environ.py
tencent_apigateway_common-0.1.11.dist-info/METADATA
tencent_apigateway_common-0.1.11.dist-info/WHEEL
tencent_apigateway_common-0.1.11.dist-info/RECORD
