Metadata-Version: 2.1
Name: tencent-apigateway-common
Version: 0.1.11
Summary: 
Requires-Python: >=3.6.2,<3.8
Classifier: Programming Language :: Python :: 3
Classifier: Programming Language :: Python :: 3.7
Requires-Dist: blue-krill (>=1.0.5,<2.0.0)
Requires-Dist: cryptography (>=3.3.1,<4.0.0)
Requires-Dist: dataclasses (>=0.7,<0.8) ; python_full_version >= "3.6.1" and python_full_version < "3.7.0"
Requires-Dist: django
Requires-Dist: djangorestframework (>=3.10,<4.0)
Requires-Dist: pypi-simple (>=0.8.0,<0.9.0)
